appkit_commons/__init__.py
appkit_commons/middleware.py
appkit_commons/registry.py
appkit_commons/security.py
appkit_commons/configuration/__init__.py
appkit_commons/configuration/base.py
appkit_commons/configuration/configuration.py
appkit_commons/configuration/logging.py
appkit_commons/configuration/secret_provider.py
appkit_commons/configuration/yaml.py
appkit_commons/database/base_repository.py
appkit_commons/database/configuration.py
appkit_commons/database/entities.py
appkit_commons/database/session.py
appkit_commons/database/sessionmanager.py
appkit_commons-1.0.1.dist-info/METADATA
appkit_commons-1.0.1.dist-info/WHEEL
appkit_commons-1.0.1.dist-info/RECORD
