Metadata-Version: 2.4
Name: appkit-commons
Version: 1.0.1
Summary: Add your description here
Project-URL: Homepage, https://github.com/jenreh/appkit
Project-URL: Documentation, https://github.com/jenreh/appkit/tree/main/docs
Project-URL: Repository, https://github.com/jenreh/appkit
Project-URL: Issues, https://github.com/jenreh/appkit/issues
Author: Jens Rehpöhler
Keywords: components,mantine,reflex,ui,web
Classifier: Intended Audience :: Developers
Classifier: License :: OSI Approved :: MIT License
Classifier: Programming Language :: Python :: 3
Classifier: Programming Language :: Python :: 3.13
Classifier: Topic :: Software Development :: Libraries :: Python Modules
Classifier: Topic :: Software Development :: User Interfaces
Requires-Python: >=3.13
Requires-Dist: colorlog>=6.10.1
Requires-Dist: cryptography>=46.0.4
Requires-Dist: pydantic-settings>=2.12.0
Requires-Dist: pyyaml>=6.0.3
Requires-Dist: sqlalchemy-utils>=0.42.1
Requires-Dist: sqlalchemy>=2.0.46
Requires-Dist: starlette>=0.50.0
Provides-Extra: azure
Requires-Dist: azure-identity==1.25.1; extra == 'azure'
Requires-Dist: azure-keyvault-secrets==4.10.0; extra == 'azure'
